mqtt_publisher/__init__.py
mqtt_publisher/config.py
mqtt_publisher/ha_discovery/__init__.py
mqtt_publisher/ha_discovery/device.py
mqtt_publisher/ha_discovery/discovery_manager.py
mqtt_publisher/ha_discovery/entity.py
mqtt_publisher/ha_discovery/publisher.py
mqtt_publisher/ha_discovery/status_sensor.py
mqtt_publisher/ha_mqtt_config/ha_mqtt_discovery.json.example
mqtt_publisher/ha_mqtt_discovery/__init__.py
mqtt_publisher/ha_mqtt_discovery/discovery.py
mqtt_publisher/ha_mqtt_discovery/topic.py
mqtt_publisher/publisher.py
ronschaeffer_mqtt_publisher-0.2.0.dist-info/LICENSE
ronschaeffer_mqtt_publisher-0.2.0.dist-info/METADATA
ronschaeffer_mqtt_publisher-0.2.0.dist-info/WHEEL
ronschaeffer_mqtt_publisher-0.2.0.dist-info/RECORD
