Metadata-Version: 2.3
Name: ronschaeffer-mqtt-publisher
Version: 0.2.0
Summary: An MQTT publisher package
License: MIT
Keywords: mqtt,publisher,iot
Author: ronschaeffer
Author-email: ron@ronschaeffer.com
Requires-Python: >=3.9,<4.0
Classifier: License :: OSI Approved :: MIT License
Classifier: Programming Language :: Python :: 3
Classifier: Programming Language :: Python :: 3.9
Classifier: Programming Language :: Python :: 3.10
Classifier: Programming Language :: Python :: 3.11
Classifier: Programming Language :: Python :: 3.12
Classifier: Programming Language :: Python :: 3.13
Requires-Dist: paho-mqtt (>=2.1.0,<3.0.0)
Requires-Dist: python-dotenv (>=1.1.1,<2.0.0)
Requires-Dist: pyyaml (>=6.0,<7.0)
Requires-Dist: typing-extensions (>=4.7.0,<5.0.0)
Project-URL: Homepage, https://github.com/ronschaeffer/mqtt_publisher
Project-URL: Repository, https://github.com/ronschaeffer/mqtt_publisher
